{
  "project_info": {
    "project_number": "623603887567",
    "project_id": "doctorplus-41a69",
    "storage_bucket": "doctorplus-41a69.firebasestorage.app"
  },
  "client": [
    {
      "client_info": {
        "mobilesdk_app_id": "1:623603887567:android:c02542da083c4508fe36ba",
        "android_client_info": {
          "package_name": "com.kis_production.Doctor"
        }
      },
      "oauth_client": [],
      "api_key": [
        {
          "current_key": "AIzaSyBUz7_og2A5_6Lb5_GAm2yFT-9_dZtDoKU"
        }
      ],
      "services": {
        "appinvite_service": {
          "other_platform_oauth_client": []
        }
      }
    }
  ],
  "configuration_version": "1"
}